Metadata-Version: 2.1
Name: odoo12-addon-connector-base-product
Version: 12.0.1.0.0.99.dev7
Summary: Connector Base Product
Home-page: http://odoo-connector.com
Author: Openerp Connector Core Editors, Odoo Community Association (OCA)
Author-email: support@odoo-community.org
License: LGPL-3
Platform: UNKNOWN
Classifier: Programming Language :: Python
Classifier: Framework :: Odoo
Classifier: Framework :: Odoo :: 12.0
Classifier: License :: OSI Approved :: GNU Lesser General Public License v3 (LGPLv3)
Requires-Python: >=3.5
Requires-Dist: odoo12-addon-connector
Requires-Dist: odoo <12.1dev,>=12.0a
